gradio_banner/__init__.py
gradio_banner/banner.py
gradio_banner/banner.pyi
gradio_banner/templates/component/index.js
gradio_banner/templates/component/style.css
gradio_banner/templates/example/index.js
gradio_banner/templates/example/style.css
gradio_banner-1.0.1.dist-info/METADATA
gradio_banner-1.0.1.dist-info/WHEEL
gradio_banner-1.0.1.dist-info/RECORD
