Metadata-Version: 2.3
Name: gradio_banner
Version: 1.0.1
Summary: A banner component for displaying important information, alerts, notifications, and types of messages within a Gradio Blocks.
Author: Daniel Ialcin Misser Westergaard
License-Expression: Apache-2.0
Keywords: alert,banner,error,gradio-custom-component,gradio-template-SimpleTextbox,info,message,notification,success,template,warning
Classifier: Development Status :: 3 - Alpha
Classifier: Operating System :: OS Independent
Classifier: Programming Language :: Python :: 3
Classifier: Programming Language :: Python :: 3 :: Only
Classifier: Programming Language :: Python :: 3.8
Classifier: Programming Language :: Python :: 3.9
Classifier: Programming Language :: Python :: 3.10
Classifier: Programming Language :: Python :: 3.11
Classifier: Topic :: Scientific/Engineering
Classifier: Topic :: Scientific/Engineering :: Artificial Intelligence
Classifier: Topic :: Scientific/Engineering :: Visualization
Requires-Python: >=3.8
Requires-Dist: gradio<5.0,>=4.0
Provides-Extra: dev
Requires-Dist: build; extra == 'dev'
Requires-Dist: twine; extra == 'dev'
